stark_qa/__init__.py
stark_qa/evaluator.py
stark_qa/load_model.py
stark_qa/load_qa.py
stark_qa/load_skb.py
stark_qa/models/__init__.py
stark_qa/models/base.py
stark_qa/models/bm25.py
stark_qa/models/colbertv2.py
stark_qa/models/llm_reranker.py
stark_qa/models/multi_vss.py
stark_qa/models/vss.py
stark_qa/retrieval/__init__.py
stark_qa/retrieval/dataset.py
stark_qa/skb/__init__.py
stark_qa/skb/amazon.py
stark_qa/skb/knowledge_base.py
stark_qa/skb/mag.py
stark_qa/skb/prime.py
stark_qa/tools/__init__.py
stark_qa/tools/args.py
stark_qa/tools/download_hf.py
stark_qa/tools/graph.py
stark_qa/tools/io.py
stark_qa/tools/loose_match.py
stark_qa/tools/node.py
stark_qa/tools/process_text.py
stark_qa/tools/seed.py
stark_qa/tools/llm_lib/__init__.py
stark_qa/tools/llm_lib/get_llm_embeddings.py
stark_qa/tools/llm_lib/get_llm_outputs.py
stark_qa/tools/llm_lib/completion/__init__.py
stark_qa/tools/llm_lib/completion/claude.py
stark_qa/tools/llm_lib/completion/gpt.py
stark_qa/tools/llm_lib/completion/huggingface.py
stark_qa/tools/llm_lib/embedding/__init__.py
stark_qa/tools/llm_lib/embedding/gritlm.py
stark_qa/tools/llm_lib/embedding/llm2vec.py
stark_qa/tools/llm_lib/embedding/openai.py
stark_qa/tools/llm_lib/embedding/voyage.py
stark_qa-0.1.3.dist-info/LICENSE
stark_qa-0.1.3.dist-info/METADATA
stark_qa-0.1.3.dist-info/WHEEL
stark_qa-0.1.3.dist-info/top_level.txt
stark_qa-0.1.3.dist-info/RECORD
