Metadata-Version: 2.1
Name: stark_qa
Version: 0.1.3
Summary: Benchmarking LLM Retrieval on Textual and Relational Knowledge Bases
Author-email: STaRK team <stark-qa@cs.stanford.edu>
Maintainer-email: STaRK team <stark-qa@cs.stanford.edu>
License: MIT License
Project-URL: Homepage, https://stark.stanford.edu/
Project-URL: Repository, https://github.com/snap-stanford/stark.git
Keywords: nlp,information-retrieval,graph,knowledge-base,semi-structured-data,multimodal,llm
Classifier: Development Status :: 4 - Beta
Classifier: Intended Audience :: Developers
Classifier: License :: OSI Approved :: MIT License
Classifier: Programming Language :: Python :: 3
Classifier: Programming Language :: Python :: 3.8
Classifier: Programming Language :: Python :: 3.9
Classifier: Programming Language :: Python :: 3.10
Classifier: Programming Language :: Python :: 3.11
Requires-Python: <3.12,>=3.8
License-File: LICENSE
Requires-Dist: anthropic >=0.27.0
Requires-Dist: bs4
Requires-Dist: bm25s
Requires-Dist: colbert-ai
Requires-Dist: gdown
Requires-Dist: gritlm
Requires-Dist: huggingface-hub
Requires-Dist: langchain
Requires-Dist: langdetect
Requires-Dist: llm2vec
Requires-Dist: multiprocess
Requires-Dist: nltk
Requires-Dist: numpy
Requires-Dist: ogb
Requires-Dist: openai
Requires-Dist: pandas
Requires-Dist: PyTDC
Requires-Dist: torch
Requires-Dist: torch-geometric
Requires-Dist: torchmetrics
Requires-Dist: tqdm
Requires-Dist: transformers
Requires-Dist: voyageai
